Metadata-Version: 2.1
Name: isgc
Version: 1.0.2
Summary: A SGPA and CGPA Calculator for Islamia University Bahawalpur Graduation Students under supervision of Malik Shahzad, a Senior Developer. Also thankful for departmental support from M. Bux Alvi Sahb and Engr. Mubashir Hussain. A motivation from Muhammad Ibrar. Also very thankful to Sundas Tariq and Laiba Saleem for contributing to this project and making it usable for all IUB Graduation Students. Some friendly support from Asim Zubair and Usman Akram
Home-page: https://github.com/ahsantariq7/isgc
Author: Ahsan Tariq
Author-email: ahsantariq0724@gmail.com
License: UNKNOWN
Project-URL: Bug Reports, https://github.com/ahsantariq7/isgc/issues
Project-URL: Source, https://github.com/ahsantariq7/isgc
Keywords: isgc, ISGC, GPA calculator education,Islamia University Bahawalpur,Ahsan Tariq,Ahsan Tariq 0724
Platform: UNKNOWN
Classifier: Development Status :: 3 - Alpha
Classifier: Intended Audience :: Education
Classifier: License :: OSI Approved :: MIT License
Classifier: Programming Language :: Python :: 3
Classifier: Programming Language :: Python :: 3.6
Classifier: Programming Language :: Python :: 3.7
Classifier: Programming Language :: Python :: 3.8
Classifier: Programming Language :: Python :: 3.9
Classifier: Programming Language :: Python :: 3.10
Classifier: Programming Language :: Python :: 3.11
Classifier: Programming Language :: Python :: 3.12
Requires-Dist: matplotlib
Requires-Dist: pyfiglet
Requires-Dist: seaborn
Requires-Dist: tabulate
